histd/__init__.py
histd/cli.py
histd-0.0.4.dist-info/METADATA
histd-0.0.4.dist-info/WHEEL
histd-0.0.4.dist-info/entry_points.txt
histd-0.0.4.dist-info/top_level.txt
histd-0.0.4.dist-info/RECORD
